pyusl/__init__.py
pyusl/usl.py
pyusl-0.0.4.dist-info/DESCRIPTION.rst
pyusl-0.0.4.dist-info/METADATA
pyusl-0.0.4.dist-info/RECORD
pyusl-0.0.4.dist-info/WHEEL
pyusl-0.0.4.dist-info/metadata.json
pyusl-0.0.4.dist-info/top_level.txt
