Metadata-Version: 2.0
Name: pyusl
Version: 0.0.4
Summary: A package for calculating Universal Scalability Law (USL)
Home-page: https://github.com/wip727/PyUSL
Author: ChangQing Wang
Author-email: wip727@gmail.com
License: MIT
Keywords: Scalability testing,Universal Scalability Law,USL
Platform: UNKNOWN
Requires-Dist: matplotlib
Requires-Dist: numpy
Requires-Dist: scipy
